odoo/addons/account_move_post_date_user/README.rst
odoo/addons/account_move_post_date_user/__init__.py
odoo/addons/account_move_post_date_user/__manifest__.py
odoo/addons/account_move_post_date_user/i18n/account_move_post_date_user.pot
odoo/addons/account_move_post_date_user/i18n/it.po
odoo/addons/account_move_post_date_user/models/__init__.py
odoo/addons/account_move_post_date_user/models/account_move.py
odoo/addons/account_move_post_date_user/readme/CONTRIBUTORS.md
odoo/addons/account_move_post_date_user/readme/DESCRIPTION.md
odoo/addons/account_move_post_date_user/static/description/icon.png
odoo/addons/account_move_post_date_user/static/description/index.html
odoo/addons/account_move_post_date_user/tests/__init__.py
odoo/addons/account_move_post_date_user/tests/test_account_move_post_date_user.py
odoo/addons/account_move_post_date_user/views/account_move.xml
odoo_addon_account_move_post_date_user-19.0.1.0.0.2.dist-info/METADATA
odoo_addon_account_move_post_date_user-19.0.1.0.0.2.dist-info/WHEEL
odoo_addon_account_move_post_date_user-19.0.1.0.0.2.dist-info/top_level.txt
odoo_addon_account_move_post_date_user-19.0.1.0.0.2.dist-info/RECORD
