Metadata-Version: 2.1
Name: odoo-addon-account_move_post_date_user
Version: 19.0.1.0.0.2
Requires-Dist: odoo==19.0.*
Summary: Trace journal entry posting date and user.
Home-page: https://github.com/OCA/account-financial-tools
License: LGPL-3
Author: ForgeFlow S.L., Odoo Community Association (OCA)
Author-email: support@odoo-community.org
Classifier: Programming Language :: Python
Classifier: Framework :: Odoo
Classifier: Framework :: Odoo :: 19.0
Classifier: License :: OSI Approved :: GNU Lesser General Public License v3 (LGPLv3)
